write_read/__init__.py
write_read/__main__.py
write_read/file_read.py
write_read/file_write.py
write_read/util/__init__.py
write_read/util/file_handler.py
write_read-1.0.0.dist-info/METADATA
write_read-1.0.0.dist-info/WHEEL
write_read-1.0.0.dist-info/top_level.txt
write_read-1.0.0.dist-info/RECORD
