Metadata-Version: 2.1
Name: write-read
Version: 1.0.0
Summary: Handling file read and write
Home-page: UNKNOWN
Author: UNKNOWN
Author-email: UNKNOWN
License: UNKNOWN
Platform: UNKNOWN
